LICENSE
README.md
pyproject.toml
setup.cfg
src/CHM/__init__.py
src/CHM/conversion.py
src/CHM/ugrid.py
src/CHM/ugrid2tiff.py
src/CHM/utils.py
src/CHM/vtu.py
src/CHM.egg-info/PKG-INFO
src/CHM.egg-info/SOURCES.txt
src/CHM.egg-info/dependency_links.txt
src/CHM.egg-info/entry_points.txt
src/CHM.egg-info/requires.txt
src/CHM.egg-info/top_level.txt
src/CHM/tools/__init__.py
src/CHM/tools/pvd_from_dir.py
src/CHM/tools/validate_json.py
src/CHM/tools/vtu2geo.py
src/CHM/tools/vtu_to_nc.py
src/CHM/tools/windmapper2mesher.py