Metadata-Version: 2.1
Name: CHM
Version: 1.4.3
Summary: python tools for CHM
Author: Chris Marsh
Project-URL: Homepage, https://github.com/Chrismarsh/mesher
Requires-Python: >=3.7
License-File: LICENSE
